Metadata-Version: 2.1
Name: mq_image_processing
Version: 0.0.1
Summary: Processamento de imagens usando combinação e transformação
Home-page: https://github.com/marianasqueiroz/image-processing-package
Author: Mariana Simões Queiroz
Author-email: marsiqueiroz@gmail.com
Requires-Python: >=3.8
Requires-Dist: matplotlib
Requires-Dist: numpy
Requires-Dist: scikit-image>=0.16.1
